algnuth/__init__.py
algnuth/ideals.py
algnuth/jacobi.py
algnuth/polynom.py
algnuth/quadratic.py
algnuth-0.0.3.dist-info/METADATA
algnuth-0.0.3.dist-info/RECORD
algnuth-0.0.3.dist-info/WHEEL
algnuth-0.0.3.dist-info/top_level.txt
