Metadata-Version: 2.1
Name: algnuth
Version: 0.0.3
Summary: Algebraic Number Theory package
Home-page: https://github.com/louisabraham/algnuth
Author: Louis Abraham
Author-email: louis.abraham@yahoo.fr
License: MIT
Keywords: algebra
Platform: UNKNOWN
Classifier: Topic :: Scientific/Engineering :: Mathematics
Requires-Dist: numpy
